odoo10_addon_stock_scanner_receipt-10.0.1.0.0.99.dev6-py3.8-nspkg.pth
odoo/addons/stock_scanner_receipt/README.rst
odoo/addons/stock_scanner_receipt/__init__.py
odoo/addons/stock_scanner_receipt/__manifest__.py
odoo/addons/stock_scanner_receipt/data/Receipt/Receipt.scenario
odoo/addons/stock_scanner_receipt/data/Receipt/scanner_scenario_step_receipt_done.py
odoo/addons/stock_scanner_receipt/data/Receipt/scanner_scenario_step_receipt_end_confirmation.py
odoo/addons/stock_scanner_receipt/data/Receipt/scanner_scenario_step_receipt_invalid_prodlot.py
odoo/addons/stock_scanner_receipt/data/Receipt/scanner_scenario_step_receipt_invalid_quantity.py
odoo/addons/stock_scanner_receipt/data/Receipt/scanner_scenario_step_receipt_location_selection.py
odoo/addons/stock_scanner_receipt/data/Receipt/scanner_scenario_step_receipt_picking_selection.py
odoo/addons/stock_scanner_receipt/data/Receipt/scanner_scenario_step_receipt_prodlot_selection.py
odoo/addons/stock_scanner_receipt/data/Receipt/scanner_scenario_step_receipt_product_selection.py
odoo/addons/stock_scanner_receipt/data/Receipt/scanner_scenario_step_receipt_quantity_selection.py
odoo/addons/stock_scanner_receipt/data/Receipt/scanner_scenario_step_receipt_unknown_location.py
odoo/addons/stock_scanner_receipt/data/Receipt/scanner_scenario_step_receipt_unknown_picking.py
odoo/addons/stock_scanner_receipt/i18n/stock_scanner_receipt.pot
odoo/addons/stock_scanner_receipt/images/scenario.png
odoo/addons/stock_scanner_receipt/readme/CONTRIBUTORS.rst
odoo/addons/stock_scanner_receipt/readme/DESCRIPTION.rst
odoo/addons/stock_scanner_receipt/readme/INSTALL.rst
odoo/addons/stock_scanner_receipt/static/description/icon.png
odoo/addons/stock_scanner_receipt/static/description/index.html
odoo10_addon_stock_scanner_receipt-10.0.1.0.0.99.dev6.dist-info/METADATA
odoo10_addon_stock_scanner_receipt-10.0.1.0.0.99.dev6.dist-info/WHEEL
odoo10_addon_stock_scanner_receipt-10.0.1.0.0.99.dev6.dist-info/namespace_packages.txt
odoo10_addon_stock_scanner_receipt-10.0.1.0.0.99.dev6.dist-info/top_level.txt
odoo10_addon_stock_scanner_receipt-10.0.1.0.0.99.dev6.dist-info/RECORD
